logicqubit/__init__.py
logicqubit/__main__.py
logicqubit/circuit.py
logicqubit/exceptions.py
logicqubit/gates.py
logicqubit/hilbert.py
logicqubit/logic.py
logicqubit/oracle.py
logicqubit/qubits.py
logicqubit/synthesis.py
logicqubit/utils.py
logicqubit/zhegalkin.py
logicqubit-1.7.9.dist-info/LICENSE
logicqubit-1.7.9.dist-info/METADATA
logicqubit-1.7.9.dist-info/WHEEL
logicqubit-1.7.9.dist-info/top_level.txt
logicqubit-1.7.9.dist-info/RECORD
