Metadata-Version: 2.1
Name: logicqubit
Version: 1.7.9
Summary: LogicQubit is a simple library for quantum computing simulation.
Home-page: https://github.com/clnrp/logicqubit
Author: Cleoner Pietralonga
Author-email: cleonerp@gmail.com
Classifier: Development Status :: 4 - Beta
Classifier: Intended Audience :: Developers
Classifier: Topic :: Scientific/Engineering :: Physics
Classifier: License :: OSI Approved :: Apache Software License
Classifier: Programming Language :: Python :: 2.7
Classifier: Programming Language :: Python :: 3
Classifier: Programming Language :: Python :: 3.4
Classifier: Programming Language :: Python :: 3.5
Classifier: Programming Language :: Python :: 3.6
Classifier: Programming Language :: Python :: 3.7
Classifier: Programming Language :: Python :: 3.8
Classifier: Programming Language :: Python :: 3.9
Classifier: Programming Language :: Python :: 3.10
Classifier: Programming Language :: Python :: 3.11
License-File: LICENSE
Requires-Dist: sympy <2,>=1.12
Requires-Dist: numpy <3,>=1.24
Requires-Dist: matplotlib <4,>=3.7
Requires-Dist: tensornetwork >=0.4.6
Provides-Extra: cuda
Requires-Dist: torch <3,>=2.2 ; extra == 'cuda'
